dict_unpack/__init__.py
dict_unpack-0.0.2.dist-info/METADATA
dict_unpack-0.0.2.dist-info/WHEEL
dict_unpack-0.0.2.dist-info/top_level.txt
dict_unpack-0.0.2.dist-info/RECORD
