Metadata-Version: 2.1
Name: dict-unpack
Version: 0.0.2
Summary: A specialized dictionary unpacking tool that allows you to expand a dictionary by unpacking internal arrays or list values, generating a list of dictionaries. Each dictionary in the list will contain a copy of all key-value pairs. This tool is designed to split arrays within JSON data into multiple records, making it easier to insert into a database.
Author-email: YiZixuan <admin@sqkkyzx.com>
License: GPL-3.0-only
Classifier: Development Status :: 3 - Alpha
Classifier: Intended Audience :: Developers
Classifier: License :: OSI Approved :: GNU General Public License v3 (GPLv3)
Classifier: Programming Language :: Python :: 3.11
